
{ 

    "data":[
        {
            "name": "Han",
            "state": "Look, kid...",
            "description": "I have got enough on my plate as it is and I...",
            "image": "pablo.jpg"
        },
        {
            "name": "Lucke",
            "state": "Your thoughts betray you...",
            "description": "I have got enough on my plate as it is and I...",
            "image": "raul.jpg"
        },
        {
            "name": "Alexis",
            "state": "You are my only hope",
            "description": "I have got enough on my plate as it is and I...",
            "image": "sanches.jpg"
        },
        {
            "name": "Andres",
            "state": "Look for a new customer",
            "description": "I have got enough on my plate as it is and I...",
            "image": "saul.jpg"
        },
        {
            "name": "Pedro",
            "state": "Time to leave",
            "description": "I have got enough on my plate as it is and I...",
            "image": "ulktimo.jpg"
        },
        {
            "name": "Leila",
            "state": "Go ahead",
            "description": "I have got enough on my plate as it is and I...",
            "image": "s.jpg"
        }
    ]
}